Metadata-Version: 2.4
Name: llm-tools-kiwix
Version: 0.1
Summary: Expose offline wiki and stack exchange archives to llms.
Author: M.Ozan Unal
License-Expression: Apache-2.0
Project-URL: Homepage, https://github.com/mozanunal/llm-tools-kiwix
Project-URL: Changelog, https://github.com/mozanunal/llm-tools-kiwix/releases
Project-URL: Issues, https://github.com/mozanunal/llm-tools-kiwix/issues
Project-URL: CI, https://github.com/mozanunal/llm-tools-kiwix/actions
Requires-Python: >=3.9
License-File: LICENSE
Requires-Dist: llm>=0.26
Requires-Dist: libzim>=3.5
Requires-Dist: strip-tags>=0.6
Provides-Extra: test
Requires-Dist: pytest; extra == "test"
Requires-Dist: llm-echo>=0.3a1; extra == "test"
Dynamic: license-file
